plover_retro_surround/__init__.py
plover_retro_surround-0.0.4.dist-info/METADATA
plover_retro_surround-0.0.4.dist-info/WHEEL
plover_retro_surround-0.0.4.dist-info/entry_points.txt
plover_retro_surround-0.0.4.dist-info/top_level.txt
plover_retro_surround-0.0.4.dist-info/zip-safe
plover_retro_surround-0.0.4.dist-info/RECORD
