Metadata-Version: 2.1
Name: plover-retro-surround
Version: 0.0.4
Summary: Surround words you previously typed with arbitrary characters
Home-page: https://github.com/elkowar/plover_retro_surround
Author: ElKowar
License: MIT
Keywords: plover_plugin plover
Platform: UNKNOWN
Requires-Dist: plover (>=4.0.0.dev6)
